Tech_In_Seconds/__init__.py
Tech_In_Seconds/agl.py
Tech_In_Seconds-1.0.5.dist-info/LICENCE
Tech_In_Seconds-1.0.5.dist-info/METADATA
Tech_In_Seconds-1.0.5.dist-info/WHEEL
Tech_In_Seconds-1.0.5.dist-info/top_level.txt
Tech_In_Seconds-1.0.5.dist-info/RECORD
